ecopipeline/__init__.py
ecopipeline/event_tracking/__init__.py
ecopipeline/event_tracking/event_tracking.py
ecopipeline/extract/__init__.py
ecopipeline/extract/extract.py
ecopipeline/load/__init__.py
ecopipeline/load/load.py
ecopipeline/transform/__init__.py
ecopipeline/transform/bayview.py
ecopipeline/transform/lbnl.py
ecopipeline/transform/transform.py
ecopipeline/utils/ConfigManager.py
ecopipeline/utils/NOAADataDownloader.py
ecopipeline/utils/__init__.py
ecopipeline/utils/unit_convert.py
ecopipeline/utils/pkls/__init__.py
ecopipeline/utils/pkls/tasseron_resistance_to_temp_3.pkl
ecopipeline/utils/pkls/tasseron_temp_to_resistance_2.pkl
ecopipeline/utils/pkls/veris_resistance_to_temp_3.pkl
ecopipeline/utils/pkls/veris_temp_to_resistance_2.pkl
ecopipeline-1.0.5.dist-info/licenses/LICENSE
ecopipeline-1.0.5.dist-info/METADATA
ecopipeline-1.0.5.dist-info/WHEEL
ecopipeline-1.0.5.dist-info/top_level.txt
ecopipeline-1.0.5.dist-info/RECORD
