Metadata-Version: 2.4
Name: ecopipeline
Version: 1.0.5
Summary: Contains functions for use in Ecotope Datapipelines
Classifier: Programming Language :: Python :: 3
Classifier: License :: OSI Approved :: GNU General Public License (GPL)
Classifier: Operating System :: OS Independent
Requires-Python: >=3.11
License-File: LICENSE
Requires-Dist: pandas>=1.5.3
Requires-Dist: numpy>=1.24.1
Requires-Dist: mysql-connector-python>=8.0.32
Requires-Dist: scikit-learn>=1.2.1
Requires-Dist: statsmodels
Requires-Dist: openmeteo_requests
Dynamic: license-file
